COPYING
LICENSE
README.txt
TODO
setup.cfg
setup.py
doc/Makefile
doc/manual.html
doc/manual.txt
doc/style.css
examples/controller_decorators/run.py
examples/controller_decorators/files/witch.comp
examples/hitcounter/readme.txt
examples/hitcounter/run.py
examples/hitcounter/someControllers.py
examples/hitcounter/files/favicon.ico
examples/hitcounter/files/index.stml
examples/hitcounter/files/slotconf.pydcmp
examples/hitcounter/files/comp/skins/default/template.stml
examples/littlewiki/littlewiki.py
examples/littlewiki/files/format_body.pycomp
examples/littlewiki/files/littlewiki.comp
examples/responses/run.py
examples/responses/files/404.html
examples/responses/files/500.html
examples/responses/files/favicon.ico
examples/responses/files/index.stml
examples/responses/files/slotconf.pydcmp
examples/responses/files/comp/skins/default/template.stml
examples/runner/run.py
examples/session/run.py
examples/session/run_pydo.py
examples/simple/run.py
examples/simple/files/favicon.ico
examples/simple/files/hello.pycomp
examples/simple/files/index.stml
examples/simple/files/skunk.jpg
examples/simple/files/slotconf.pydcmp
examples/simple/files/comp/skins/default/template.stml
examples/simple/files/robots/index.stml
examples/simpleauth/auth.conf
examples/simpleauth/run.py
examples/simpleauth/files/index.html
examples/simpleauth/files/login.comp
examples/simpleauth/files/protected/index.html
examples/simpleauth/files/protected/logout.html
examples/simplelog/run.py
examples/webtags/run.py
examples/webtags/files/500.html
examples/webtags/files/blowup.stml
examples/webtags/files/index.stml
examples/webtags/files/next.stml
src/skunk/__init__.py
src/skunk/userlogger.py
src/skunk.web.egg-info/PKG-INFO
src/skunk.web.egg-info/SOURCES.txt
src/skunk.web.egg-info/dependency_links.txt
src/skunk.web.egg-info/entry_points.txt
src/skunk.web.egg-info/requires.txt
src/skunk.web.egg-info/top_level.txt
src/skunk/cache/__init__.py
src/skunk/cache/base.py
src/skunk/cache/decorator.py
src/skunk/cache/diskCache.py
src/skunk/cache/djangoCache.py
src/skunk/cache/exceptions.py
src/skunk/cache/log.py
src/skunk/cache/memcachedCache.py
src/skunk/cache/memoryCache.py
src/skunk/cache/policy.py
src/skunk/components/__init__.py
