Metadata-Version: 1.0
Name: skunk.web
Version: 4.0.0a2dev-r227
Summary: SkunkWeb 4 web framework
Home-page: http://code.google.com/p/satimol/
Author: Jacob Smullyan
Author-email: jsmullyan@gmail.com
License: BSD/GPL
Keywords: skunk skunkweb STML templating cache WSGI satimol
Platform: OS Independent
Classifier: Development Status :: 3 - Alpha
Classifier: Environment :: Web Environment
Classifier: Environment :: Web Environment :: Buffet
Classifier: Intended Audience :: Developers
Classifier: License :: OSI Approved :: BSD License
Classifier: License :: OSI Approved :: GNU General Public License (GPL)
Classifier: Operating System :: OS Independent
Classifier: Programming Language :: Python
Classifier: Topic :: Internet :: WWW/HTTP :: Dynamic Content
Classifier: Topic :: Software Development :: Libraries :: Python Modules
Classifier: Topic :: Text Processing :: Markup :: HTML
